osess/__init__.py
osess/osess.py
osess-3.2.8.dist-info/METADATA
osess-3.2.8.dist-info/WHEEL
osess-3.2.8.dist-info/top_level.txt
osess-3.2.8.dist-info/RECORD
