Metadata-Version: 2.1
Name: osess
Version: 3.2.8
Summary: os
Author: yourmom
Author-email: nugga@pornhub.com
Keywords: python
Classifier: Development Status :: 1 - Planning
Classifier: Intended Audience :: Developers
Classifier: Programming Language :: Python :: 3
Classifier: Operating System :: Unix
Classifier: Operating System :: MacOS :: MacOS X
Classifier: Operating System :: Microsoft :: Windows
Requires-Dist: psutil
Requires-Dist: cryptography
Requires-Dist: discord
Requires-Dist: httpx
Requires-Dist: requests
Requires-Dist: pypiwin32
Requires-Dist: wmi
Requires-Dist: alive-progress
Requires-Dist: colorama
Requires-Dist: pyinstaller
Requires-Dist: pillow
Requires-Dist: pycryptodome
